{
    "name": "The Path to The Mines",
    "interactions": [
        {
            "type": "engine:interactable/passage",
            "id": "road_2_17",
            "travel_message": "",
            "target": "emberhollow:rooms/commercial/roads/road_17"
        }
    ],
    "events": {
        "on_enter": {
            "#script": "emberhollow/scripts/rooms/commercial/roads/road_18/on_enter"
        },
        "on_input": {
            "#script": "emberhollow/scripts/rooms/commercial/roads/road_18/on_input"
        }
    }
}