{
    "name": "Center Street",
    "interactions": [
        {
            "type": "engine:interactable/passage",
            "id": "",
            "target": "energia_city:rooms/city_center"
        },
        {
            "type": "engine:interactable/passage",
            "id": "",
            "target": "energia_city:rooms/park"
        }
    ],
    "events": {
        "on_enter": {
            "#script": "energia_city/scripts/center_street/on_enter"
        },
        "on_input": {
            "#script": "energia_city/scripts/center_street/on_input"
        }
    }
}